niwrap_dcm2niix/dcm2niix/__init__.py
niwrap_dcm2niix/dcm2niix/dcm2niix.py
niwrap_dcm2niix-0.8.3.dist-info/WHEEL
niwrap_dcm2niix-0.8.3.dist-info/METADATA
niwrap_dcm2niix-0.8.3.dist-info/RECORD
