Metadata-Version: 2.4
Name: niwrap-dcm2niix
Version: 0.8.3
Summary: Neuroimaging wrappers.
Author: CMI DAIR
License-Expression: MIT
Requires-Dist: styxdefs>=0.6.0,<0.7.0
Requires-Python: >=3.10
